CHANGELOG.md
LICENSE
MANIFEST.in
Makefile
README.md
setup.cfg
setup.py
tox.ini
px_django_actions_tracker.egg-info/PKG-INFO
px_django_actions_tracker.egg-info/SOURCES.txt
px_django_actions_tracker.egg-info/dependency_links.txt
px_django_actions_tracker.egg-info/requires.txt
px_django_actions_tracker.egg-info/top_level.txt
pxd_actions_tracker/__init__.py
pxd_actions_tracker/apps.py
pxd_actions_tracker/conf.py
pxd_actions_tracker/const.py
pxd_actions_tracker/domains.py
pxd_actions_tracker/middleware.py
pxd_actions_tracker/signals.py
pxd_actions_tracker/utils.py
pxd_actions_tracker/cases/__init__.py
pxd_actions_tracker/cases/lifecycle.py
pxd_actions_tracker/cases/tracking.py
pxd_actions_tracker/storages/__init__.py
pxd_actions_tracker/storages/db/__init__.py
pxd_actions_tracker/storages/db/admin.py
pxd_actions_tracker/storages/db/apps.py
pxd_actions_tracker/storages/db/models.py
pxd_actions_tracker/storages/db/signals.py
pxd_actions_tracker/storages/db/storage.py
pxd_actions_tracker/storages/db/migrations/0001_initial.py
pxd_actions_tracker/storages/db/migrations/__init__.py
pxd_actions_tracker/trackers/__init__.py
pxd_actions_tracker/trackers/track_logs.py
pxd_actions_tracker/trackers/track_requests.py
pxd_actions_tracker/trackers/track_views.py