Metadata-Version: 2.1
Name: px-django-actions-tracker
Version: 0.1.7
Summary: Simple in-app actions tracker.
Home-page: UNKNOWN
Author: Alex Tkachenko
Author-email: preusx.dev@gmail.com
License: MIT License
Platform: UNKNOWN
Classifier: Development Status :: 2 - Pre-Alpha
Classifier: Programming Language :: Python :: 3
Classifier: Framework :: Django
Classifier: Intended Audience :: Developers
Classifier: Topic :: Utilities
Classifier: License :: OSI Approved :: MIT License
Classifier: Operating System :: OS Independent
Requires-Python: >=3.6
Provides-Extra: dev
License-File: LICENSE
